claude_api_desktop/__init__.py
claude_api_desktop/client.py
claude_api_desktop/main.py
claude_api_desktop/py.typed
claude_api_desktop/database/__init__.py
claude_api_desktop/database/manager.py
claude_api_desktop/dialogs/__init__.py
claude_api_desktop/dialogs/branch.py
claude_api_desktop/dialogs/help.py
claude_api_desktop/dialogs/history.py
claude_api_desktop/dialogs/settings.py
claude_api_desktop-1.0.0.dist-info/licenses/LICENSE
claude_api_desktop-1.0.0.dist-info/METADATA
claude_api_desktop-1.0.0.dist-info/WHEEL
claude_api_desktop-1.0.0.dist-info/entry_points.txt
claude_api_desktop-1.0.0.dist-info/top_level.txt
claude_api_desktop-1.0.0.dist-info/RECORD
