Metadata-Version: 2.4
Name: claude-api-desktop
Version: 1.0.0
Summary: A modern desktop client for the Anthropic Claude API with streaming support and extended context capabilities
Author-email: Anthony Maio <anthony.maio@gmail.com>
Maintainer-email: Anthony Maio <anthony.maio@gmail.com>
Project-URL: Homepage, https://github.com/anthony-maio/claude-api-desktop
Project-URL: Documentation, https://github.com/anthony-maio/claude-api-desktop#readme
Project-URL: Repository, https://github.com/anthony-maio/claude-api-desktop
Project-URL: Bug Tracker, https://github.com/anthony-maio/claude-api-desktop/issues
Project-URL: Feature Requests, https://github.com/anthony-maio/claude-api-desktop/discussions
Project-URL: Changelog, https://github.com/anthony-maio/claude-api-desktop/releases
Keywords: claude,anthropic,ai,chatbot,api-client,desktop-application,streaming,gui,artificial-intelligence,machine-learning,natural-language-processing,llm,conversation-branching
Classifier: Development Status :: 4 - Beta
Classifier: Intended Audience :: Developers
Classifier: Intended Audience :: End Users/Desktop
Classifier: Topic :: Software Development :: Libraries :: Python Modules
Classifier: Topic :: Communications :: Chat
Classifier: Topic :: Scientific/Engineering :: Artificial Intelligence
Classifier: Topic :: Desktop Environment
Classifier: Programming Language :: Python :: 3
Classifier: Programming Language :: Python :: 3.8
Classifier: Programming Language :: Python :: 3.9
Classifier: Programming Language :: Python :: 3.10
Classifier: Programming Language :: Python :: 3.11
Classifier: Programming Language :: Python :: 3.12
Classifier: Operating System :: OS Independent
Classifier: Operating System :: Microsoft :: Windows
Classifier: Operating System :: POSIX :: Linux
Classifier: Operating System :: MacOS
Classifier: Environment :: X11 Applications
Classifier: Environment :: Win32 (MS Windows)
Classifier: Environment :: MacOS X
Requires-Python: >=3.8
License-File: LICENSE
Requires-Dist: requests>=2.31.0
Requires-Dist: Pillow>=10.0.0
Provides-Extra: dev
Requires-Dist: pytest>=7.0.0; extra == "dev"
Requires-Dist: pytest-cov>=4.0.0; extra == "dev"
Requires-Dist: black>=23.0.0; extra == "dev"
Requires-Dist: flake8>=6.0.0; extra == "dev"
Requires-Dist: mypy>=1.0.0; extra == "dev"
Requires-Dist: isort>=5.12.0; extra == "dev"
Requires-Dist: pre-commit>=3.0.0; extra == "dev"
Provides-Extra: test
Requires-Dist: pytest>=7.0.0; extra == "test"
Requires-Dist: pytest-cov>=4.0.0; extra == "test"
Requires-Dist: pytest-mock>=3.10.0; extra == "test"
Requires-Dist: pytest-asyncio>=0.21.0; extra == "test"
Provides-Extra: docs
Requires-Dist: sphinx>=6.0.0; extra == "docs"
Requires-Dist: sphinx-rtd-theme>=1.2.0; extra == "docs"
Requires-Dist: myst-parser>=1.0.0; extra == "docs"
Dynamic: license-file
